Metadata-Version: 2.4
Name: PyPDFForm-reducto
Version: 3.8.2.5
Summary: The Python library for PDF forms. Forked and maintained by Reducto AI.
Author: Jinge Li
Maintainer-email: Reducto AI <support@reducto.ai>
License-Expression: MIT
Project-URL: Homepage, https://github.com/reductoai/PyPDFForm-reducto
Project-URL: Documentation, https://github.com/reductoai/PyPDFForm-reducto
Project-URL: Website, https://reducto.ai
Project-URL: Original Project, https://github.com/chinapandaman/PyPDFForm
Classifier: Development Status :: 5 - Production/Stable
Classifier: Intended Audience :: Developers
Classifier: Programming Language :: Python :: 3
Classifier: Programming Language :: Python :: 3 :: Only
Classifier: Programming Language :: Python :: 3.10
Classifier: Programming Language :: Python :: 3.11
Classifier: Programming Language :: Python :: 3.12
Classifier: Programming Language :: Python :: 3.13
Classifier: Programming Language :: Python :: 3.14
Classifier: Operating System :: OS Independent
Classifier: Topic :: Software Development :: Libraries :: Python Modules
Requires-Python: >=3.10
License-File: LICENSE
Requires-Dist: cryptography>=45.0.0
Requires-Dist: fonttools<5.0.0,>=4.60.1
Requires-Dist: pikepdf>=9.4.2
Requires-Dist: pillow>=10.0.0
Requires-Dist: pypdf<7.0.0,>=6.1.0
Requires-Dist: reportlab<5.0.0,>=4.4.0
Provides-Extra: dev
Requires-Dist: black<26.0.0,>=25.11.0; extra == "dev"
Requires-Dist: coverage<8.0.0,>=7.12.0; extra == "dev"
Requires-Dist: isort<8.0.0,>=7.0.0; extra == "dev"
Requires-Dist: jsonschema<5.0.0,>=4.25.1; extra == "dev"
Requires-Dist: mkdocs<2.0.0,>=1.6.1; extra == "dev"
Requires-Dist: pudb<2026.0.0,>=2025.1.3; extra == "dev"
Requires-Dist: pylint<5.0.0,>=4.0.3; extra == "dev"
Requires-Dist: pyright<2.0.0,>=1.1.407; extra == "dev"
Requires-Dist: pytest<10.0.0,>=9.0.1; extra == "dev"
Requires-Dist: requests<3.0.0,>=2.32.5; extra == "dev"
Requires-Dist: ruff<1.0.0,>=0.14.6; extra == "dev"
Dynamic: license-file
